setup.py
activecollab/__init__.py
activecollab/constants.py
activecollab/exceptions.py
activecollab/library.py
activecollab/settings.py
pyacollab.egg-info/PKG-INFO
pyacollab.egg-info/SOURCES.txt
pyacollab.egg-info/dependency_links.txt
pyacollab.egg-info/top_level.txt