Metadata-Version: 1.0
Name: pyacollab
Version: 0.3.0
Summary: Library to interact with Active Collab, a Basecamp like PM tool
Home-page: https://github.com/jaymzcd/pyacollab
Author: Jaymz Campbell
Author-email: jaymz@jaymz.eu
License: UNKNOWN
Platform: UNKNOWN
